{
  "version": 0.1,
  "locale": "en",
  "entries": {
    "aadd25a89867": "<Globe0></Globe0> Language {expression0}",
    "0b054301b57d": "Select Language",
    "9426f7803679": "All content auto-translates via <span0>Lingo.dev</span0>",
    "1c1b1599025c": "Start Learning",
    "767db59dd383": "Join Sign Jam",
    "2862c9e1b2e4": "SignEdu – Multilingual Sign Language Learning Platform",
    "cd61a944cf48": "SignEdu is interactive multilingual sign language learning platform using AI for real-time gesture feedback and cross-language collaboration. Break barriers in global education—start signing today!",
    "4c942e4dbefb": "Lesson not found.",
    "94b9f9f52fa9": "Lesson not found.",
    "b24f016ea03b": "Lesson Complete!",
    "89ff8d388b61": "You scored {score} out of {expression0} ({percent}%)",
    "1cabcb47cff7": "Try Again",
    "d19bf32bb996": "All Lessons",
    "f971a3a4315d": "Sign {expression0} of {expression1}",
    "549a339ce2bf": "{score} pts",
    "9ab9060ebe43": "🤟",
    "e623e9856280": "Which sign is being shown?",
    "0ba2e78b19a5": "Correct! Great job!",
    "b114ee3171ab": "Next"
  }
}